pywctl/__init__.py
pywctl/main.py
pywctl-0.1.2b0.dist-info/LICENSE
pywctl-0.1.2b0.dist-info/METADATA
pywctl-0.1.2b0.dist-info/WHEEL
pywctl-0.1.2b0.dist-info/top_level.txt
pywctl-0.1.2b0.dist-info/RECORD
