Metadata-Version: 2.1
Name: pywctl
Version: 0.1.2b0
Summary: A utility to connect you, using python, to iwd, using iwctl, in ash. Made specifically for snakeware.
Home-page: https://github.com/sorroweater/pywctl
Author: Akshat Deshpande
Author-email: akshat.deshpande@icloud.com
License: UNKNOWN
Platform: UNKNOWN
Classifier: Programming Language :: Python :: 3
Classifier: License :: OSI Approved :: MIT License
Classifier: Operating System :: OS Independent
Requires-Python: >=3.9
